setup.py
sentry_argstagging/__init__.py
sentry_argstagging/plugin.py
sentry_argstagging.egg-info/PKG-INFO
sentry_argstagging.egg-info/SOURCES.txt
sentry_argstagging.egg-info/dependency_links.txt
sentry_argstagging.egg-info/entry_points.txt
sentry_argstagging.egg-info/requires.txt
sentry_argstagging.egg-info/top_level.txt