Metadata-Version: 1.1
Name: sentry-argstagging
Version: 0.0.1
Summary: Sentry Pulgin to set tags by using arguments of Message event.
Home-page: https://github.com/hirokiky/sentry_argstagging
Author: Hiroki KIYOHARA
Author-email: hirokiky@gmail.com
License: UNKNOWN
Platform: UNKNOWN
Classifier: Development Status :: 1 - Planning
Classifier: Environment :: Plugins
Classifier: Framework :: Django
Classifier: Intended Audience :: Developers
Classifier: License :: OSI Approved :: MIT License
Classifier: Programming Language :: Python
Classifier: Topic :: Software Development :: Libraries :: Python Modules
